spotify_playlists_mover/__init__.py
spotify_playlists_mover/__main__.py
spotify_playlists_mover/moving_methods.py
spotify_playlists_mover-1.0.0.dist-info/entry_points.txt
spotify_playlists_mover-1.0.0.dist-info/LICENSE
spotify_playlists_mover-1.0.0.dist-info/WHEEL
spotify_playlists_mover-1.0.0.dist-info/METADATA
spotify_playlists_mover-1.0.0.dist-info/RECORD
