Metadata-Version: 2.1
Name: spotify_playlists_mover
Version: 1.0.0
Summary: Move all your Spotify playlists and saved songs to a new account
Keywords: Spotify
Author-email: Alberto Pasqualetto <39854348+albertopasqualetto@users.noreply.github.com>
Requires-Python: >=3.7
Classifier: Programming Language :: Python :: 3
Classifier: Environment :: Console
Classifier: License :: OSI Approved :: Apache Software License
Classifier: Operating System :: OS Independent
Classifier: Topic :: Utilities
Requires-Dist: spotipy>=2.20.0
Project-URL: Bug Tracker, https://github.com/albertopasqualetto/spotify-playlists-mover/issues
Project-URL: Homepage, https://github.com/albertopasqualetto/spotify-playlists-mover
